mediawiki_api_wrapper/__init__.py
mediawiki_api_wrapper/interface.py
mediawiki_api_wrapper/login_and_editing.py
mediawiki_api_wrapper/query.py
mediawiki_api_wrapper/retrying_connection.py
mediawiki_api_wrapper-0.0.4.dist-info/LICENSE
mediawiki_api_wrapper-0.0.4.dist-info/METADATA
mediawiki_api_wrapper-0.0.4.dist-info/WHEEL
mediawiki_api_wrapper-0.0.4.dist-info/top_level.txt
mediawiki_api_wrapper-0.0.4.dist-info/RECORD
