Metadata-Version: 2.2
Name: mediawiki_api_wrapper
Version: 0.0.4
Summary: A small wrapper around mediawiki API
Home-page: https://codeberg.org/matkoniecz/mediawiki_api_python_wrapper
Author: Mateusz Konieczny
Classifier: Programming Language :: Python :: 3
Classifier: License :: OSI Approved :: MIT License
Classifier: Operating System :: OS Independent
License-File: LICENSE
Requires-Dist: urllib3
Requires-Dist: simplejson
Dynamic: author
Dynamic: classifier
Dynamic: description
Dynamic: description-content-type
Dynamic: home-page
Dynamic: requires-dist
Dynamic: summary
